langchain_openrouter/__init__.py
langchain_openrouter/openrouter.py
langchain_openrouter-0.0.1.dist-info/METADATA
langchain_openrouter-0.0.1.dist-info/WHEEL
langchain_openrouter-0.0.1.dist-info/top_level.txt
langchain_openrouter-0.0.1.dist-info/RECORD
