Metadata-Version: 2.1
Name: langchain_openrouter
Version: 0.0.1
Summary: OpenRouter large language models for LangChain.
Home-page: https://github.com/StanMathers/langchain-openrouter
License: MIT
Platform: UNKNOWN
Classifier: Intended Audience :: Developers
Classifier: Programming Language :: Python :: 3.10
Classifier: Programming Language :: Python :: 3.11
Classifier: Programming Language :: Python :: 3.12
Requires-Python: >=3.10
